Workbook

Sheet About Me
B2: Hey, I'm Liliane.
B3: You work hard for your money. But is it creating the life you're working so hard for?
B5: I'm a full-time cybersecurity consultant at a Big Four firm. I work a demanding job, and alongside my 9–5 I support my mum, who receives care at home after her cerebral haemorrhage. Balancing both is demanding, so I know how little time is left at the end of the day. Everything here comes from my own experience: I paid off €30,000 of debt and I'm building wealth beside my career with the same system I share here. I don't teach this from the outside. I've experienced it myself.
B6: You have a demanding career, bills to pay and people who depend on you. You earn a respectable income. Yet despite everything you do, you don't always feel as financially secure or independent as you thought you would.
B7: How do I build a financially secure future without missing out on the people and moments that matter most today?
B8: I know that feeling. I started as a flight attendant working toward becoming a pilot, until COVID changed those plans. I rebuilt my path in cybersecurity consulting. My income grew, but financial security didn't automatically follow. In my 20s I took on loans for my study fees, made wrong financial decisions and even fell for an online scam: I was heavily into trading without knowing much about it. My rule since then: only invest in what you understand. I paid off €30,000 of debt not by first earning more, but by understanding my finances and making deliberate changes. Now in my 30s, this is what I wish someone had told me in my 20s.
B10: WHY I REALLY BUILT THIS
B11: My mum is 83. When she had her cerebral haemorrhage, I realised how valuable time really is, and how little of it I had left. For years I worked long hours and stayed late almost every single day, because I believed climbing the corporate ladder was what success meant. But true success is realising what truly matters in life, and then taking the steps, one by one, that lead you there. We only get this one life. I want to spend as much time with her as I possibly can. Not someday, but now.
B12: Most of the financial advice out there told me to quit my job, hustle harder or get rich fast. That's unrealistic unless you're willing to risk your financial security, and when people depend on you, that's not a risk worth taking. None were made for someone with a demanding career and a mum who needs them. I wished I'd had a clear, honest plan for the few hours I actually had. So I built it for myself. You shouldn't need a wake-up call to start.
B13: That's why I created the TRUST Sheet. No judgment. No unrealistic promises. No complicated jargon. Just a practical starting point for making your money work toward the life you actually want.
B15: WHO THIS IS FOR
B16: ✓ Your financial progress doesn't reflect the effort you put into your career.
... B46: Educational information only, not individualised financial or investment advice. The TRUST Sheet helps you organise and understand your finances; it doesn't guarantee financial outcomes. Your financial information stays in your own copy of the workbook unless you choose to share it.

Sheet How to Use
B2: How to Use
B3: About 20 minutes to set up, 15 minutes a week to run. Built for busy weeks.
B5: FIRST SNAPSHOT · ABOUT 20 MINUTES
B6: 1 · Fill the yellow cells | C6: Every cell with a pale yellow background and blue text is yours to edit. Everything else calculates itself. The rows already filled in are EXAMPLES: overwrite or delete them.
B7: 2 · Go tab by tab, in order | C7: T Track → R Reclaim → U Understand → S Save → T Time. Then add any side income on Income Streams.
B8: 3 · Read your KEEP dashboard | C8: It shows what you keep, your Freedom Level (0–6) and the one next step that matters now.
B9: 4 · Review once a month | C9: Copy this month's dashboard numbers into Monthly Review. 12 rows, one per month. Watch your level climb.
B11: EVERY WEEK · 15 MINUTES
B12: Weekly money check | C12: Open KEEP and look at what you keep. Add new costs or income. Move this week's saving or debt payment.
B13: Heavy week? | C13: Caring for someone, deadlines, illness: open the KEEP dashboard, look at one number, close it. That counts. The system is built to pause without breaking.
B15: COLOUR KEY
B16: Yellow cell, blue text | C16: Your input
B17: Black text | C17: Calculated: please don't overwrite
B18: Bordeaux text | C18: Money going out or still owed (debt)
C20: © cybercnslt.com · Liliane · @cyber_cnslt · For personal use by the purchaser only, please don't resell or share.

Sheet T · Track
B2: T · Track
B3: List what comes in and what goes out in a normal month. Yearly costs? Divide by 12. Debt minimum payments are a Need. Don't list savings transfers here: what's left over is what you KEEP.
B5: MONEY IN (net, per month)
B6: Source | C6: Note | E6: € / month
B7: Salary (net) | C7: Main job | E7: 2500
B8: Side income | C8: Total from Income Streams tab | E8: ='Income Streams'!G23 -> 60
B9: Benefits / allowances | C9: e.g. child benefit, care allowance | E9: 0
B13: Total money in | E13: =SUM(E7:E12) -> 2560
B15: MONEY OUT (per month)
B16: Expense | C16: Category | D16: Need / Want | E16: € / month | F16: Note
B17: Rent / mortgage | C17: Housing | D17: Need | E17: 900 | F17: Example rows: overwrite with yours
B18: Electricity, internet, phone | C18: Utilities & phone | D18: Need | E18: 140
B19: Groceries | C19: Groceries | D19: Need | E19: 320
B20: Public transport / fuel | C20: Transport | D20: Need | E20: 90
B21: Insurance | C21: Insurance | D21: Need | E21: 80
B22: Care support for mum | C22: Caregiving | D22: Need | E22: 150
B23: Credit card minimum | C23: Debt payments | D23: Need | E23: 60
B24: Streaming & apps | C24: Subscriptions | D24: Want | E24: 45
B25: Eating out & takeaway | C25: Eating out | D25: Want | E25: 120
B26: Clothes & shopping | C26: Shopping | D26: Want | E26: 100
B58: Needs (your baseline) | E58: =SUMIF(D17:D56,"Need",E17:E56) -> 1740
B59: Wants | E59: =SUMIF(D17:D56,"Want",E17:E56) -> 265
B60: of which caregiving | E60: =SUMIF(C17:C56,"Caregiving",E17:E56) -> 150
B61: Unsorted (pick Need or Want) | E61: =SUM(E17:E56)-E58-E59 -> 0
B62: KEEP (in − needs − wants) | E62: =E13-E58-E59 -> 555
B63: Keep rate | E63: =IF(E13>0,E62/E13,0) -> 0.21679688

Sheet R · Reclaim
B2: R · Reclaim
B3: Go through bank statements for 10 minutes. Every subscription, fee and contract goes here. Decide: Keep, Cut, Reduce or Renegotiate. One call to a provider can be worth hundreds a year.
B5: Subscription / cost | C5: Now € / month | D5: Decision | E5: New € / month | F5: Reclaimed € / month | G5: Next action
B6: Second streaming service | C6: 13 | D6: Cut | E6: 0 | F6: =IF(OR(C6="",D6="",D6="Keep"),0,MAX(0,C6-N(E6))) -> 13 | G6: Cancel before renewal on the 15th
B7: Gym (not used since spring) | C7: 35 | D7: Reduce | E7: 15 | F7: =IF(OR(C7="",D7="",D7="Keep"),0,MAX(0,C7-N(E7))) -> 20 | G7: Switch to off-peak plan
B8: Mobile contract | C8: 40 | D8: Renegotiate | E8: 25 | F8: =IF(OR(C8="",D8="",D8="Keep"),0,MAX(0,C8-N(E8))) -> 15 | G8: Call and ask for current tariff
B9: Cloud storage | C9: 3 | D9: Keep | E9: 3 | F9: =IF(OR(C9="",D9="",D9="Keep"),0,MAX(0,C9-N(E9))) -> 0
F10: =IF(OR(C10="",D10="",D10="Keep"),0,MAX(0,C10-N(E10))) -> 0
F11: =IF(OR(C11="",D11="",D11="Keep"),0,MAX(0,C11-N(E11))) -> 0
F12: =IF(OR(C12="",D12="",D12="Keep"),0,MAX(0,C12-N(E12))) -> 0
F13: =IF(OR(C13="",D13="",D13="Keep"),0,MAX(0,C13-N(E13))) -> 0
F14: =IF(OR(C14="",D14="",D14="Keep"),0,MAX(0,C14-N(E14))) -> 0
F15: =IF(OR(C15="",D15="",D15="Keep"),0,MAX(0,C15-N(E15))) -> 0
F16: =IF(OR(C16="",D16="",D16="Keep"),0,MAX(0,C16-N(E16))) -> 0
F17: =IF(OR(C17="",D17="",D17="Keep"),0,MAX(0,C17-N(E17))) -> 0
F18: =IF(OR(C18="",D18="",D18="Keep"),0,MAX(0,C18-N(E18))) -> 0
F19: =IF(OR(C19="",D19="",D19="Keep"),0,MAX(0,C19-N(E19))) -> 0
F20: =IF(OR(C20="",D20="",D20="Keep"),0,MAX(0,C20-N(E20))) -> 0
F21: =IF(OR(C21="",D21="",D21="Keep"),0,MAX(0,C21-N(E21))) -> 0
... F30: =IF(OR(C30="",D30="",D30="Keep"),0,MAX(0,C30-N(E30))) -> 0
B32: Reclaimable per month | F32: =SUM(F6:F30) -> 48
B33: Reclaimable per year | F33: =F32*12 -> 576
B35: Rule: reclaimed money gets a job the same day. Move it to your buffer or debt before it disappears into everyday spending.

Sheet U · Understand
B2: U · Understand
B3: Debt first: what you owe, what it costs you each month, and which one to attack first (highest interest = highest priority). Then: what is one hour of your working life really worth?
B5: Debt | C5: Balance € | D5: Interest % / year | E5: Minimum € / month | F5: Extra € / month | G5: Interest cost € / month | H5: Months to clear | I5: Priority
B6: Credit card | C6: 1500 | D6: 0.199 | E6: 60 | F6: 40 | G6: =IF(N(C6)>0,C6*N(D6)/12,0) -> 24.875 | H6: =IF(N(C6)<=0,"",IF(N(E6)+N(F6)<=G6,"Payment too low",ROUNDUP(IF(N(D6)=0,C6/(N(E6)+N(F6)),NPER(D6/12,-(N(E6)+N(F6)),C6)),0))) -> 18 | I6: =IF(N(C6)<=0,"",COUNTIFS($C$6:$C$15,">0",$D$6:$D$15,">"&N(D6))+1) -> 1
B7: Overdraft | C7: 0 | D7: 0.12 | E7: 0 | F7: 0 | G7: =IF(N(C7)>0,C7*N(D7)/12,0) -> 0 | H7: =IF(N(C7)<=0,"",IF(N(E7)+N(F7)<=G7,"Payment too low",ROUNDUP(IF(N(D7)=0,C7/(N(E7)+N(F7)),NPER(D7/12,-(N(E7)+N(F7)),C7)),0))) | I7: =IF(N(C7)<=0,"",COUNTIFS($C$6:$C$15,">0",$D$6:$D$15,">"&N(D7))+1)
G8: =IF(N(C8)>0,C8*N(D8)/12,0) -> 0 | H8: =IF(N(C8)<=0,"",IF(N(E8)+N(F8)<=G8,"Payment too low",ROUNDUP(IF(N(D8)=0,C8/(N(E8)+N(F8)),NPER(D8/12,-(N(E8)+N(F8)),C8)),0))) | I8: =IF(N(C8)<=0,"",COUNTIFS($C$6:$C$15,">0",$D$6:$D$15,">"&N(D8))+1)
G9: =IF(N(C9)>0,C9*N(D9)/12,0) -> 0 | H9: =IF(N(C9)<=0,"",IF(N(E9)+N(F9)<=G9,"Payment too low",ROUNDUP(IF(N(D9)=0,C9/(N(E9)+N(F9)),NPER(D9/12,-(N(E9)+N(F9)),C9)),0))) | I9: =IF(N(C9)<=0,"",COUNTIFS($C$6:$C$15,">0",$D$6:$D$15,">"&N(D9))+1)
G10: =IF(N(C10)>0,C10*N(D10)/12,0) -> 0 | H10: =IF(N(C10)<=0,"",IF(N(E10)+N(F10)<=G10,"Payment too low",ROUNDUP(IF(N(D10)=0,C10/(N(E10)+N(F10)),NPER(D10/12,-(N(E10)+N(F10)),C10)),0))) | I10: =IF(N(C10)<=0,"",COUNTIFS($C$6:$C$15,">0",$D$6:$D$15,">"&N(D10))+1)
G11: =IF(N(C11)>0,C11*N(D11)/12,0) -> 0 | H11: =IF(N(C11)<=0,"",IF(N(E11)+N(F11)<=G11,"Payment too low",ROUNDUP(IF(N(D11)=0,C11/(N(E11)+N(F11)),NPER(D11/12,-(N(E11)+N(F11)),C11)),0))) | I11: =IF(N(C11)<=0,"",COUNTIFS($C$6:$C$15,">0",$D$6:$D$15,">"&N(D11))+1)
G12: =IF(N(C12)>0,C12*N(D12)/12,0) -> 0 | H12: =IF(N(C12)<=0,"",IF(N(E12)+N(F12)<=G12,"Payment too low",ROUNDUP(IF(N(D12)=0,C12/(N(E12)+N(F12)),NPER(D12/12,-(N(E12)+N(F12)),C12)),0))) | I12: =IF(N(C12)<=0,"",COUNTIFS($C$6:$C$15,">0",$D$6:$D$15,">"&N(D12))+1)
G13: =IF(N(C13)>0,C13*N(D13)/12,0) -> 0 | H13: =IF(N(C13)<=0,"",IF(N(E13)+N(F13)<=G13,"Payment too low",ROUNDUP(IF(N(D13)=0,C13/(N(E13)+N(F13)),NPER(D13/12,-(N(E13)+N(F13)),C13)),0))) | I13: =IF(N(C13)<=0,"",COUNTIFS($C$6:$C$15,">0",$D$6:$D$15,">"&N(D13))+1)
G14: =IF(N(C14)>0,C14*N(D14)/12,0) -> 0 | H14: =IF(N(C14)<=0,"",IF(N(E14)+N(F14)<=G14,"Payment too low",ROUNDUP(IF(N(D14)=0,C14/(N(E14)+N(F14)),NPER(D14/12,-(N(E14)+N(F14)),C14)),0))) | I14: =IF(N(C14)<=0,"",COUNTIFS($C$6:$C$15,">0",$D$6:$D$15,">"&N(D14))+1)
G15: =IF(N(C15)>0,C15*N(D15)/12,0) -> 0 | H15: =IF(N(C15)<=0,"",IF(N(E15)+N(F15)<=G15,"Payment too low",ROUNDUP(IF(N(D15)=0,C15/(N(E15)+N(F15)),NPER(D15/12,-(N(E15)+N(F15)),C15)),0))) | I15: =IF(N(C15)<=0,"",COUNTIFS($C$6:$C$15,">0",$D$6:$D$15,">"&N(D15))+1)
B17: Total debt | C17: =SUM(C6:C15) -> 1500 | D17: Priority 1 = highest interest rate. Send every extra euro there, pay minimums on the rest. Months to clear is an estimate with fixed payments.
B18: Interest you pay / month | C18: =SUM(G6:G15) -> 24.875
B19: Interest you pay / year | C19: =C18*12 -> 298.5
B22: WHAT ONE HOUR OF YOUR LIFE IS WORTH
B23: Item | C23: Value
B24: Net money in / month | C24: ='T · Track'!E7 -> 2500 | D24: Keep your first hour: the first hour of every workday is paid to you, not to your bills. Set up a standing transfer for this amount on payday. If it's too much right now, start with a quarter of it.
B25: Contract hours / week | C25: 39
B26: Unpaid overtime / week | C26: 4
B27: Commute hours / week | C27: 5
B28: Real hours / month | C28: =(N(C25)+N(C26)+N(C27))*52/12 -> 208
B29: Your real hourly value | C29: =IF(C28>0,C24/C28,0) -> 12.019231 | D29: Before any purchase over €50, divide the price by your real hourly value. That's how many hours of your life it costs.
B30: Workdays / month | C30: 21
B31: Keep your first hour / month | C31: =C29*N(C30) -> 252.40385

Sheet S · Save
B2: S · Save
B3: The order matters. First a 1-month buffer, then clear consumer debt, then a full emergency fund (3 months; 6 if you're a carer, self-employed or the only earner). Then goals.
B5: EMERGENCY FUND
B6: Item | C6: Value
B7: Monthly needs (baseline) | C7: ='T · Track'!E58 -> 1740 | D7: Keep it separate from your everyday account, easy to reach within a day or two, and boring. This money is insurance, not an investment.
B8: Months of safety you want | C8: 3
B9: Starter buffer (1 month) | C9: =C7 -> 1740
B10: Full emergency fund target | C10: =C7*N(C8) -> 5220
B11: Saved so far | C11: 1200
B12: Progress | C12: =IF(C10>0,MIN(1,N(C11)/C10),0) -> 0.22988506
B13: Monthly transfer to it | C13: 250
B14: Months until full fund | C14: =IF(N(C11)>=C10,"Done ✓",IF(N(C13)>0,ROUNDUP((C10-N(C11))/C13,0),"Add a transfer")) -> 17
B17: GOAL POTS (sinking funds)
B18: Goal | C18: Target € | D18: Saved € | E18: € / month | F18: Months left | G18: Progress
B19: Care costs & time off | C19: 1500 | D19: 300 | E19: 75 | F19: =IF(N(C19)=0,"",IF(N(D19)>=C19,"Done ✓",IF(N(E19)>0,ROUNDUP((C19-N(D19))/E19,0),"–"))) -> 16 | G19: =IF(N(C19)>0,MIN(1,N(D19)/C19),0) -> 0.2
B20: Christmas & birthdays | C20: 600 | D20: 100 | E20: 50 | F20: =IF(N(C20)=0,"",IF(N(D20)>=C20,"Done ✓",IF(N(E20)>0,ROUNDUP((C20-N(D20))/E20,0),"–"))) -> 10 | G20: =IF(N(C20)>0,MIN(1,N(D20)/C20),0) -> 0.16666667
B21: Holiday with family | C21: 1800 | D21: 250 | E21: 100 | F21: =IF(N(C21)=0,"",IF(N(D21)>=C21,"Done ✓",IF(N(E21)>0,ROUNDUP((C21-N(D21))/E21,0),"–"))) -> 16 | G21: =IF(N(C21)>0,MIN(1,N(D21)/C21),0) -> 0.13888889
F22: =IF(N(C22)=0,"",IF(N(D22)>=C22,"Done ✓",IF(N(E22)>0,ROUNDUP((C22-N(D22))/E22,0),"–"))) | G22: =IF(N(C22)>0,MIN(1,N(D22)/C22),0) -> 0
F23: =IF(N(C23)=0,"",IF(N(D23)>=C23,"Done ✓",IF(N(E23)>0,ROUNDUP((C23-N(D23))/E23,0),"–"))) | G23: =IF(N(C23)>0,MIN(1,N(D23)/C23),0) -> 0
F24: =IF(N(C24)=0,"",IF(N(D24)>=C24,"Done ✓",IF(N(E24)>0,ROUNDUP((C24-N(D24))/E24,0),"–"))) | G24: =IF(N(C24)>0,MIN(1,N(D24)/C24),0) -> 0
F25: =IF(N(C25)=0,"",IF(N(D25)>=C25,"Done ✓",IF(N(E25)>0,ROUNDUP((C25-N(D25))/E25,0),"–"))) | G25: =IF(N(C25)>0,MIN(1,N(D25)/C25),0) -> 0
F26: =IF(N(C26)=0,"",IF(N(D26)>=C26,"Done ✓",IF(N(E26)>0,ROUNDUP((C26-N(D26))/E26,0),"–"))) | G26: =IF(N(C26)>0,MIN(1,N(D26)/C26),0) -> 0
F27: =IF(N(C27)=0,"",IF(N(D27)>=C27,"Done ✓",IF(N(E27)>0,ROUNDUP((C27-N(D27))/E27,0),"–"))) | G27: =IF(N(C27)>0,MIN(1,N(D27)/C27),0) -> 0
F28: =IF(N(C28)=0,"",IF(N(D28)>=C28,"Done ✓",IF(N(E28)>0,ROUNDUP((C28-N(D28))/E28,0),"–"))) | G28: =IF(N(C28)>0,MIN(1,N(D28)/C28),0) -> 0
B30: Total monthly to goal pots | E30: =SUM(E19:E28) -> 225
B31: Total monthly saving (fund + pots) | E31: =N(C13)+E30 -> 475
B32: Still unassigned from KEEP | E32: ='T · Track'!E62-E31 -> 80
B33: If 'still unassigned' is negative, your plan spends more than you keep. Lower a transfer until it's zero or positive.

Sheet T · Time
B2: T · Time
B3: A week has 168 hours. Map a realistic one, including care and recovery. Then decide which hours you'll protect for the people you love, and how many (if any) go to building options.
B5: Area | C5: Hours / week now | D5: Hours / week goal | E5: What would change it?
B6: Sleep | C6: 49 | D6: 52 | E6: Phone out of the bedroom
B7: Paid work (incl. overtime) | C7: 43 | D7: 40 | E7: Stop answering email after 7pm
B8: Commute | C8: 5 | D8: 5
B9: Caregiving | C9: 10 | D9: 10 | E9: Ask sibling for one fixed day
B10: Household & admin | C10: 10 | D10: 8 | E10: One big shop per week
B11: Family & friends time | C11: 12 | D11: 16 | E11: Protected Sunday afternoon
B12: Health & movement | C12: 3 | D12: 4 | E12: Walk at lunch
B13: Building options (learning / side income) | C13: 3 | D13: 4 | E13: Two 2-hour blocks, Tue & Sat
B14: Rest & yourself | C14: 10 | D14: 10
B19: Hours planned | C19: =SUM(C6:C17) -> 145 | D19: =SUM(D6:D17) -> 149
B20: Unplanned hours (of 168) | C20: =168-C19 -> 23 | D20: =168-D19 -> 19
B22: Family time gained / week | C22: =SUMIF(B6:B17,"Family*",D6:D17)-SUMIF(B6:B17,"Family*",C6:C17) -> 4
B23: Family time gained / year | C23: =C22*52 -> 208
B25: Negative unplanned hours mean the week doesn't fit. Something has to go before anything new comes in. Never take side-project hours out of sleep or family first.
B28: Your hourly value at work | C28: ='U · Understand'!C29 -> 12.019231 | D28: This is roughly what extra income or savings would need to replace if you reduced your paid hours to your goal. A concrete target for the Income Streams tab.
B29: Value of the work hours you want back / year | C29: =MAX(0,SUMIF(B6:B17,"Paid work*",C6:C17)-SUMIF(B6:B17,"Paid work*",D6:D17))*52*C28 -> 1875

Sheet Income Streams
B2: Income Streams
B3: Build one stream at a time, beside your career. Log every stream here, including a raise you negotiated. Watch € per hour: a stream that pays less than your job per hour must be buying you something else (skills, assets, freedom later).
B5: Stream | C5: Type | D5: Status | E5: Hours / week | F5: Started (month) | G5: € / month (net) | H5: € per hour | I5: Next small step
B6: Salary raise negotiated | C6: Career (raise/promotion) | D6: Earning | E6: 0 | F6: 2026-03 | G6: 150 | H6: =IF(N(E6)>0,N(G6)/(E6*52/12),IF(N(G6)>0,"no time logged","")) -> no time logged | I6: Prepare next review in March
B7: Cybersecurity starter guide | C7: Digital product | D7: Testing | E7: 3 | F7: 2026-08 | G7: 60 | H7: =IF(N(E7)>0,N(G7)/(E7*52/12),IF(N(G7)>0,"no time logged","")) -> 4.6153846 | I7: Post 3 reels pointing to it
B8: UGC for a skincare brand | C8: UGC | D8: Idea | E8: 0 | G8: 0 | H8: =IF(N(E8)>0,N(G8)/(E8*52/12),IF(N(G8)>0,"no time logged","")) | I8: Make 2 sample videos
H9: =IF(N(E9)>0,N(G9)/(E9*52/12),IF(N(G9)>0,"no time logged",""))
H10: =IF(N(E10)>0,N(G10)/(E10*52/12),IF(N(G10)>0,"no time logged",""))
H11: =IF(N(E11)>0,N(G11)/(E11*52/12),IF(N(G11)>0,"no time logged",""))
H12: =IF(N(E12)>0,N(G12)/(E12*52/12),IF(N(G12)>0,"no time logged",""))
H13: =IF(N(E13)>0,N(G13)/(E13*52/12),IF(N(G13)>0,"no time logged",""))
H14: =IF(N(E14)>0,N(G14)/(E14*52/12),IF(N(G14)>0,"no time logged",""))
H15: =IF(N(E15)>0,N(G15)/(E15*52/12),IF(N(G15)>0,"no time logged",""))
H16: =IF(N(E16)>0,N(G16)/(E16*52/12),IF(N(G16)>0,"no time logged",""))
H17: =IF(N(E17)>0,N(G17)/(E17*52/12),IF(N(G17)>0,"no time logged",""))
H18: =IF(N(E18)>0,N(G18)/(E18*52/12),IF(N(G18)>0,"no time logged",""))
H19: =IF(N(E19)>0,N(G19)/(E19*52/12),IF(N(G19)>0,"no time logged",""))
H20: =IF(N(E20)>0,N(G20)/(E20*52/12),IF(N(G20)>0,"no time logged",""))
H21: =IF(N(E21)>0,N(G21)/(E21*52/12),IF(N(G21)>0,"no time logged",""))
B23: Total extra income / month | G23: =SUMIF(C6:C21,"<>Career (raise/promotion)",G6:G21) -> 60
B24: Career growth / month (in salary) | G24: =SUMIF(C6:C21,"Career (raise/promotion)",G6:G21) -> 150
B25: Hours / week on streams | E25: =SUM(E6:E21) -> 3
B26: Share of your needs covered by extra income | G26: =IF('T · Track'!E58>0,G23/'T · Track'!E58,0) -> 0.034482759
B28: A raise already shows up in your net salary on T · Track, so it is counted separately and not added to side income twice.

Sheet KEEP Dashboard
B2: KEEP — Know your Earnings to Escape your Paycheck
B3: Your month on one page. Nothing to fill in here: it reads every other tab.
B5: YOUR FREEDOM LEVEL
B6: =INDEX(Lists!$F$1:$F$7,C9+1) -> Level 1 · Stable | E6: =CHOOSE(C9+1,"Next step: more goes out than comes in. Use R · Reclaim and cut wants until KEEP is at least €0.","Next step: build a starter buffer of one month of needs before anything else.","Next step: clear consumer debt, highest interest first (Priority 1 on U · Understand).","Next step: grow the buffer into your full emergency fund on S · Save.","Next step: you are secure. Learn long-term investing basics and start ONE income stream.","Next step: extra income covers 25%+ of needs. Keep investing; decide what time you want back.","You have choices. Extra income covers your baseline. Decide on your terms how much you want to work.") -> Next step: build a starter buffer of one month of needs before anything else.
B9: Level number | C9: =IF(C14<0,0,IF(C22<C13,1,IF(C20>0,2,IF(C22<C23,3,IF(C25<0.25*C13,4,IF(C25<C13,5,6)))))) -> 1
B11: MONEY | E11: TIME & OPTIONS
B12: Money in / month | C12: ='T · Track'!E13 -> 2560 | E12: 1 hour of your life is worth | F12: ='U · Understand'!C29 -> 12.019231
B13: Needs (baseline) | C13: ='T · Track'!E58 -> 1740 | E13: Keep your first hour / month | F13: ='U · Understand'!C31 -> 252.40385
B14: What you KEEP / month | C14: ='T · Track'!E62 -> 555 | E14: Hours / week on income streams | F14: ='Income Streams'!E25 -> 3
B15: Keep rate | C15: ='T · Track'!E63 -> 0.21679688 | E15: Needs covered by extra income | F15: ='Income Streams'!G26 -> 0.034482759
B16: Wants | C16: ='T · Track'!E59 -> 265 | E16: Family time gained / week (goal) | F16: ='T · Time'!C22 -> 4
B17: Reclaimable / month | C17: ='R · Reclaim'!F32 -> 48 | E17: Unassigned KEEP after savings plan | F17: ='S · Save'!E32 -> 80
B18: Reclaimable / year | C18: ='R · Reclaim'!F33 -> 576 | E18: Career growth / month | F18: ='Income Streams'!G24 -> 150
B19: SAFETY
B20: Debt to clear | C20: ='U · Understand'!C17 -> 1500 | E20: THE FREEDOM LADDER
B21: Interest you pay / year | C21: ='U · Understand'!C19 -> 298.5 | E21: 0 · Overwhelmed: more out than in
B22: Emergency fund saved | C22: ='S · Save'!C11 -> 1200 | E22: 1 · Stable: KEEP is €0 or more
B23: Emergency fund target | C23: ='S · Save'!C10 -> 5220 | E23: 2 · Buffered: 1 month of needs saved
B24: Fund progress | C24: ='S · Save'!C12 -> 0.22988506 | E24: 3 · Debt-free: consumer debt cleared
B25: Extra income / month | C25: ='Income Streams'!G23 -> 60 | E25: 4 · Secure: full emergency fund
E26: 5 · Flexible: extra income ≥ 25% of needs
E27: 6 · Free to choose: extra income ≥ needs
B28: Your career is the engine. Keep your first hour, and keep going. — Liliane
B29: Educational tool. Not financial advice.

Sheet Monthly Review
B2: Monthly Review
B3: Once a month, 15 minutes: copy the numbers from KEEP into a new row. The level calculates itself. Write one win, however small.
B5: Month | C5: Money in | D5: Needs | E5: Wants | F5: KEEP | G5: Keep rate | H5: Emergency fund | I5: Debt | J5: Extra income | K5: Level | L5: One win this month
B6: Sep 2026 | C6: 2500 | D6: 1650 | E6: 330 | F6: =IF(C6="","",C6-N(D6)-N(E6)) -> 520 | G6: =IF(N(C6)>0,F6/C6,"") -> 0.208 | H6: 1000 | I6: 1500 | J6: 0 | K6: =IF(C6="","",INDEX(Lists!$F$1:$F$7,1+IF(F6<0,0,IF(N(H6)<N(D6),1,IF(N(I6)>0,2,IF(N(H6)<N(D6)*'S · Save'!$C$8,3,IF(N(J6)<0.25*N(D6),4,IF(N(J6)<N(D6),5,6)))))))) -> Level 1 · Stable | L6: Cancelled 2 subscriptions
B7: Oct 2026 | C7: 2560 | D7: 1640 | E7: 265 | F7: =IF(C7="","",C7-N(D7)-N(E7)) -> 655 | G7: =IF(N(C7)>0,F7/C7,"") -> 0.25585938 | H7: 1200 | I7: 1400 | J7: 60 | K7: =IF(C7="","",INDEX(Lists!$F$1:$F$7,1+IF(F7<0,0,IF(N(H7)<N(D7),1,IF(N(I7)>0,2,IF(N(H7)<N(D7)*'S · Save'!$C$8,3,IF(N(J7)<0.25*N(D7),4,IF(N(J7)<N(D7),5,6)))))))) -> Level 1 · Stable | L7: First €60 from my guide
F8: =IF(C8="","",C8-N(D8)-N(E8)) | G8: =IF(N(C8)>0,F8/C8,"") | K8: =IF(C8="","",INDEX(Lists!$F$1:$F$7,1+IF(F8<0,0,IF(N(H8)<N(D8),1,IF(N(I8)>0,2,IF(N(H8)<N(D8)*'S · Save'!$C$8,3,IF(N(J8)<0.25*N(D8),4,IF(N(J8)<N(D8),5,6))))))))
F9: =IF(C9="","",C9-N(D9)-N(E9)) | G9: =IF(N(C9)>0,F9/C9,"") | K9: =IF(C9="","",INDEX(Lists!$F$1:$F$7,1+IF(F9<0,0,IF(N(H9)<N(D9),1,IF(N(I9)>0,2,IF(N(H9)<N(D9)*'S · Save'!$C$8,3,IF(N(J9)<0.25*N(D9),4,IF(N(J9)<N(D9),5,6))))))))
F10: =IF(C10="","",C10-N(D10)-N(E10)) | G10: =IF(N(C10)>0,F10/C10,"") | K10: =IF(C10="","",INDEX(Lists!$F$1:$F$7,1+IF(F10<0,0,IF(N(H10)<N(D10),1,IF(N(I10)>0,2,IF(N(H10)<N(D10)*'S · Save'!$C$8,3,IF(N(J10)<0.25*N(D10),4,IF(N(J10)<N(D10),5,6))))))))
F11: =IF(C11="","",C11-N(D11)-N(E11)) | G11: =IF(N(C11)>0,F11/C11,"") | K11: =IF(C11="","",INDEX(Lists!$F$1:$F$7,1+IF(F11<0,0,IF(N(H11)<N(D11),1,IF(N(I11)>0,2,IF(N(H11)<N(D11)*'S · Save'!$C$8,3,IF(N(J11)<0.25*N(D11),4,IF(N(J11)<N(D11),5,6))))))))
F12: =IF(C12="","",C12-N(D12)-N(E12)) | G12: =IF(N(C12)>0,F12/C12,"") | K12: =IF(C12="","",INDEX(Lists!$F$1:$F$7,1+IF(F12<0,0,IF(N(H12)<N(D12),1,IF(N(I12)>0,2,IF(N(H12)<N(D12)*'S · Save'!$C$8,3,IF(N(J12)<0.25*N(D12),4,IF(N(J12)<N(D12),5,6))))))))
F13: =IF(C13="","",C13-N(D13)-N(E13)) | G13: =IF(N(C13)>0,F13/C13,"") | K13: =IF(C13="","",INDEX(Lists!$F$1:$F$7,1+IF(F13<0,0,IF(N(H13)<N(D13),1,IF(N(I13)>0,2,IF(N(H13)<N(D13)*'S · Save'!$C$8,3,IF(N(J13)<0.25*N(D13),4,IF(N(J13)<N(D13),5,6))))))))
F14: =IF(C14="","",C14-N(D14)-N(E14)) | G14: =IF(N(C14)>0,F14/C14,"") | K14: =IF(C14="","",INDEX(Lists!$F$1:$F$7,1+IF(F14<0,0,IF(N(H14)<N(D14),1,IF(N(I14)>0,2,IF(N(H14)<N(D14)*'S · Save'!$C$8,3,IF(N(J14)<0.25*N(D14),4,IF(N(J14)<N(D14),5,6))))))))
F15: =IF(C15="","",C15-N(D15)-N(E15)) | G15: =IF(N(C15)>0,F15/C15,"") | K15: =IF(C15="","",INDEX(Lists!$F$1:$F$7,1+IF(F15<0,0,IF(N(H15)<N(D15),1,IF(N(I15)>0,2,IF(N(H15)<N(D15)*'S · Save'!$C$8,3,IF(N(J15)<0.25*N(D15),4,IF(N(J15)<N(D15),5,6))))))))
F16: =IF(C16="","",C16-N(D16)-N(E16)) | G16: =IF(N(C16)>0,F16/C16,"") | K16: =IF(C16="","",INDEX(Lists!$F$1:$F$7,1+IF(F16<0,0,IF(N(H16)<N(D16),1,IF(N(I16)>0,2,IF(N(H16)<N(D16)*'S · Save'!$C$8,3,IF(N(J16)<0.25*N(D16),4,IF(N(J16)<N(D16),5,6))))))))
F17: =IF(C17="","",C17-N(D17)-N(E17)) | G17: =IF(N(C17)>0,F17/C17,"") | K17: =IF(C17="","",INDEX(Lists!$F$1:$F$7,1+IF(F17<0,0,IF(N(H17)<N(D17),1,IF(N(I17)>0,2,IF(N(H17)<N(D17)*'S · Save'!$C$8,3,IF(N(J17)<0.25*N(D17),4,IF(N(J17)<N(D17),5,6))))))))

Sheet Lists
A1: Housing | B1: Need | C1: Keep | D1: Career (raise/promotion) | E1: Idea | F1: Level 0 · Overwhelmed
A2: Utilities & phone | B2: Want | C2: Cut | D2: Freelance / consulting | E2: Testing | F2: Level 1 · Stable
A3: Groceries | C3: Reduce | D3: Digital product | E3: Earning | F3: Level 2 · Buffered
A4: Transport | C4: Renegotiate | D4: UGC | E4: Paused | F4: Level 3 · Debt-free
A5: Insurance | D5: YouTube / content | F5: Level 4 · Secure
A6: Childcare | D6: Brand deals | F6: Level 5 · Flexible
A7: Caregiving | D7: Affiliate | F7: Level 6 · Free to choose
A8: Health | D8: Investment income
A9: Debt payments | D9: Other
A10: Subscriptions
A11: Eating out
A12: Shopping
A13: Fun & hobbies
A14: Gifts
A15: Travel
A16: Other
